setup.py
pimpleFlux/__init__.py
pimpleFlux.egg-info/PKG-INFO
pimpleFlux.egg-info/SOURCES.txt
pimpleFlux.egg-info/dependency_links.txt
pimpleFlux.egg-info/entry_points.txt
pimpleFlux.egg-info/requires.txt
pimpleFlux.egg-info/top_level.txt
pimpleFlux.egg-info/zip-safe
pimpleFlux/r1_6/__init__.py
pimpleFlux/r1_6_dev/__init__.py
pimpleFlux/r2_0_0/__init__.py
pimpleFlux/r2_1_0/__init__.py
pimpleFlux/r2_1_1/__init__.py